{"algorithm": {"name": "GTurbo", "parameters": {"epsilon_b": 0.01, "epsilon_n": 0, "lam": 200, "beta": 0.9995, "alpha": 0.95, "max_age": 200, "radius": 0.5}}, "results": {"100": {"ss": 0.2064308375120163, "cluster_score": 0.16418609387073865, "#clusters": 54, "#instances": 96, "distribution": {"1": 26, "2": 20, "3": 4, "4": 3, "6": 1}, "avg/mean instances / cluster": 1.7777777777777777, "max instances of any cluster": 1, "min instances of any cluster": 6, "matches_results": {"distribution #matches": {"1": 40, "2": 30, "0": 16, "4": 7, "3": 5, "5": 1, "6": 1}, "distribution #potential": {"2": 45, "1": 26, "4": 13, "3": 8, "6": 8}, "distribution avg similarity range": {"75 - 80": 28, "80 - 85": 25, "70 - 75": 22, "85 - 90": 10, "65 - 70": 6, "90 - 95": 4, "60 - 65": 2, "95 - 100": 2, "55 - 60": 1}, "distribution avg quality range": {"20 - 25": 29, "30 - 35": 17, "25 - 30": 17, "45 - 50": 8, "15 - 20": 7, "40 - 45": 7, "35 - 40": 3, "80 - 85": 2, "85 - 90": 2, "10 - 15": 2, "70 - 75": 1, "5 - 10": 1, "90 - 95": 1, "65 - 70": 1, "100 - 105": 1, "50 - 55": 1}, "distribution avg real range": {"45 - 50": 29, "50 - 55": 23, "55 - 60": 17, "60 - 65": 10, "40 - 45": 7, "65 - 70": 5, "90 - 95": 3, "80 - 85": 2, "35 - 40": 1, "75 - 80": 1, "70 - 75": 1, "85 - 90": 1}, "distribution avg matches range": {"50 - 55": 31, "55 - 60": 29, "60 - 65": 11, "65 - 70": 5, "90 - 95": 3, "80 - 85": 2, "75 - 80": 1, "70 - 75": 1, "85 - 90": 1}, "distribution matches range": {"50 - 55": 63, "55 - 60": 44, "60 - 65": 22, "65 - 70": 11, "80 - 85": 6, "90 - 95": 4, "70 - 75": 3, "75 - 80": 1}, "% at least 1 match": 0.84, "avg #matches": 1.54, "max #matches of a user": 6, "min #matches of a user": 0, "avg #potential": 2.4, "max #potential of a user": 6, "min #potential of a user": 1, "avg matches score": 0.5003736555666772, "avg real score": 0.5562610919381816, "avg similarity score": 0.7858574535946051, "avg quality score": 0.32666473028175813}}, "200": {"ss": 0.1857607066631317, "cluster_score": 0.32130189586884167, "#clusters": 78, "#instances": 179, "distribution": {"1": 33, "2": 20, "3": 17, "4": 3, "6": 2, "7": 1, "11": 1, "13": 1}, "avg/mean instances / cluster": 2.2948717948717947, "max instances of any cluster": 1, "min instances of any cluster": 13, "matches_results": {"distribution #matches": {"1": 28, "2": 23, "3": 12, "0": 12, "4": 6, "6": 5, "5": 4, "7": 4, "11": 2, "8": 2, "12": 2}, "distribution #potential": {"1": 26, "3": 23, "2": 14, "6": 12, "7": 8, "13": 7, "11": 5, "4": 5}, "distribution avg similarity range": {"80 - 85": 28, "75 - 80": 24, "70 - 75": 21, "85 - 90": 13, "65 - 70": 7, "90 - 95": 4, "95 - 100": 2, "60 - 65": 1}, "distribution avg quality range": {"20 - 25": 24, "25 - 30": 16, "30 - 35": 13, "40 - 45": 10, "35 - 40": 8, "15 - 20": 5, "70 - 75": 3, "45 - 50": 3, "10 - 15": 3, "85 - 90": 3, "5 - 10": 2, "90 - 95": 2, "55 - 60": 2, "50 - 55": 1, "75 - 80": 1, "65 - 70": 1, "100 - 105": 1, "60 - 65": 1, "80 - 85": 1}, "distribution avg real range": {"45 - 50": 24, "50 - 55": 24, "55 - 60": 16, "60 - 65": 12, "40 - 45": 5, "80 - 85": 3, "90 - 95": 3, "70 - 75": 3, "75 - 80": 3, "85 - 90": 3, "65 - 70": 2, "35 - 40": 2}, "distribution avg matches range": {"55 - 60": 33, "50 - 55": 25, "60 - 65": 13, "80 - 85": 3, "90 - 95": 3, "70 - 75": 3, "75 - 80": 3, "85 - 90": 3, "65 - 70": 2}, "distribution matches range": {"50 - 55": 111, "55 - 60": 80, "60 - 65": 36, "65 - 70": 18, "80 - 85": 10, "70 - 75": 8, "75 - 80": 5, "90 - 95": 4, "85 - 90": 2}, "% at least 1 match": 0.88, "avg #matches": 2.74, "max #matches of a user": 12, "min #matches of a user": 0, "avg #potential": 4.17, "max #potential of a user": 13, "min #potential of a user": 1, "avg matches score": 0.5402951562227931, "avg real score": 0.5757857424502895, "avg similarity score": 0.7947678780672334, "avg quality score": 0.3568036068333455}}, "300": {"ss": 0.20232537388801575, "cluster_score": 0.4303737087044881, "#clusters": 94, "#instances": 248, "distribution": {"1": 41, "2": 21, "3": 12, "4": 7, "5": 4, "6": 2, "9": 2, "7": 2, "12": 1, "17": 1, "8": 1}, "avg/mean instances / cluster": 2.6382978723404253, "max instances of any cluster": 1, "min instances of any cluster": 8, "matches_results": {"distribution #matches": {"1": 34, "2": 20, "0": 12, "5": 8, "6": 6, "3": 5, "9": 4, "4": 3, "8": 3, "10": 2, "7": 2, "15": 1}, "distribution #potential": {"1": 35, "2": 17, "3": 11, "9": 10, "6": 6, "5": 5, "7": 5, "17": 5, "8": 3, "4": 2, "12": 1}, "distribution avg similarity range": {"75 - 80": 28, "80 - 85": 27, "70 - 75": 18, "85 - 90": 15, "90 - 95": 5, "95 - 100": 3, "65 - 70": 2, "55 - 60": 1, "60 - 65": 1}, "distribution avg quality range": {"20 - 25": 19, "25 - 30": 17, "30 - 35": 12, "40 - 45": 11, "35 - 40": 10, "45 - 50": 6, "85 - 90": 5, "15 - 20": 4, "10 - 15": 4, "50 - 55": 3, "70 - 75": 2, "0 - 5": 2, "100 - 105": 2, "90 - 95": 1, "65 - 70": 1, "80 - 85": 1}, "distribution avg real range": {"55 - 60": 23, "50 - 55": 20, "45 - 50": 19, "60 - 65": 13, "65 - 70": 7, "85 - 90": 4, "80 - 85": 3, "40 - 45": 3, "90 - 95": 3, "30 - 35": 1, "35 - 40": 1, "75 - 80": 1, "70 - 75": 1, "95 - 100": 1}, "distribution avg matches range": {"55 - 60": 32, "50 - 55": 20, "60 - 65": 15, "65 - 70": 8, "85 - 90": 4, "80 - 85": 3, "90 - 95": 3, "75 - 80": 1, "70 - 75": 1, "95 - 100": 1}, "distribution matches range": {"50 - 55": 100, "55 - 60": 89, "60 - 65": 42, "65 - 70": 22, "80 - 85": 10, "70 - 75": 10, "90 - 95": 6, "85 - 90": 5, "75 - 80": 1, "95 - 100": 1}, "% at least 1 match": 0.88, "avg #matches": 2.86, "max #matches of a user": 15, "min #matches of a user": 0, "avg #potential": 4.17, "max #potential of a user": 17, "min #potential of a user": 1, "avg matches score": 0.5474314815400411, "avg real score": 0.5860697542471198, "avg similarity score": 0.8029965250981009, "avg quality score": 0.36914298339613877}}, "400": {"ss": 0.20473834872245789, "cluster_score": 0.5509953071860981, "#clusters": 99, "#instances": 321, "distribution": {"1": 38, "2": 22, "4": 10, "3": 8, "6": 6, "5": 5, "9": 3, "11": 2, "13": 2, "21": 1, "8": 1, "10": 1}, "avg/mean instances / cluster": 3.242424242424242, "max instances of any cluster": 1, "min instances of any cluster": 10, "matches_results": {"distribution #matches": {"1": 33, "2": 13, "3": 10, "0": 10, "5": 8, "6": 5, "9": 4, "10": 3, "11": 3, "8": 3, "7": 2, "12": 2, "4": 2, "13": 1, "19": 1}, "distribution #potential": {"1": 29, "5": 13, "9": 11, "2": 10, "4": 7, "8": 6, "21": 5, "6": 4, "3": 4, "11": 4, "0": 3, "13": 3, "10": 1}, "distribution avg similarity range": {"80 - 85": 29, "75 - 80": 22, "70 - 75": 17, "85 - 90": 15, "90 - 95": 5, "65 - 70": 4, "0 - 5": 3, "95 - 100": 3, "60 - 65": 2}, "distribution avg quality range": {"25 - 30": 19, "20 - 25": 14, "35 - 40": 13, "30 - 35": 10, "45 - 50": 8, "40 - 45": 6, "15 - 20": 6, "0 - 5": 5, "10 - 15": 4, "85 - 90": 4, "90 - 95": 3, "70 - 75": 2, "50 - 55": 2, "100 - 105": 2, "65 - 70": 1, "80 - 85": 1}, "distribution avg real range": {"55 - 60": 24, "50 - 55": 22, "45 - 50": 13, "60 - 65": 9, "65 - 70": 7, "40 - 45": 6, "85 - 90": 6, "0 - 5": 3, "90 - 95": 3, "80 - 85": 2, "30 - 35": 1, "35 - 40": 1, "75 - 80": 1, "70 - 75": 1, "95 - 100": 1}, "distribution avg matches range": {"55 - 60": 37, "50 - 55": 19, "60 - 65": 12, "65 - 70": 8, "85 - 90": 6, "90 - 95": 3, "80 - 85": 2, "75 - 80": 1, "70 - 75": 1, "95 - 100": 1}, "distribution matches range": {"50 - 55": 128, "55 - 60": 110, "60 - 65": 56, "65 - 70": 23, "80 - 85": 11, "70 - 75": 10, "90 - 95": 10, "85 - 90": 9, "75 - 80": 2, "95 - 100": 1}, "% at least 1 match": 0.9, "avg #matches": 3.6, "max #matches of a user": 19, "min #matches of a user": 0, "avg #potential": 5.23, "max #potential of a user": 21, "min #potential of a user": 0, "avg matches score": 0.5608901476751377, "avg real score": 0.5720780485084579, "avg similarity score": 0.7794791638039384, "avg quality score": 0.3646769332129774}}, "500": {"ss": 0.18313126266002655, "cluster_score": 0.622166975706115, "#clusters": 112, "#instances": 365, "distribution": {"1": 46, "2": 19, "4": 14, "3": 9, "6": 8, "5": 5, "10": 2, "11": 2, "8": 2, "13": 1, "21": 1, "12": 1, "14": 1, "7": 1}, "avg/mean instances / cluster": 3.2589285714285716, "max instances of any cluster": 1, "min instances of any cluster": 7, "matches_results": {"distribution #matches": {"1": 33, "0": 16, "2": 10, "3": 8, "4": 8, "11": 5, "7": 4, "5": 3, "8": 3, "6": 3, "10": 2, "9": 2, "14": 1, "12": 1, "19": 1}, "distribution #potential": {"1": 32, "4": 13, "2": 9, "0": 8, "8": 7, "10": 7, "5": 6, "12": 4, "11": 3, "7": 3, "21": 3, "3": 2, "6": 2, "14": 1}, "distribution avg similarity range": {"80 - 85": 29, "75 - 80": 18, "85 - 90": 18, "70 - 75": 11, "0 - 5": 8, "65 - 70": 6, "90 - 95": 4, "95 - 100": 3, "60 - 65": 2, "55 - 60": 1}, "distribution avg quality range": {"25 - 30": 22, "30 - 35": 11, "35 - 40": 10, "0 - 5": 10, "20 - 25": 9, "40 - 45": 8, "45 - 50": 7, "70 - 75": 4, "10 - 15": 4, "15 - 20": 3, "90 - 95": 3, "85 - 90": 3, "100 - 105": 2, "80 - 85": 2, "50 - 55": 1, "65 - 70": 1}, "distribution avg real range": {"50 - 55": 21, "55 - 60": 20, "60 - 65": 12, "45 - 50": 10, "0 - 5": 8, "40 - 45": 6, "65 - 70": 6, "80 - 85": 5, "90 - 95": 3, "85 - 90": 3, "75 - 80": 2, "95 - 100": 2, "30 - 35": 1, "35 - 40": 1}, "distribution avg matches range": {"55 - 60": 31, "50 - 55": 17, "60 - 65": 14, "65 - 70": 7, "80 - 85": 5, "90 - 95": 3, "85 - 90": 3, "75 - 80": 2, "95 - 100": 2}, "distribution matches range": {"50 - 55": 111, "55 - 60": 100, "60 - 65": 54, "65 - 70": 20, "70 - 75": 12, "90 - 95": 11, "80 - 85": 10, "85 - 90": 8, "75 - 80": 4, "95 - 100": 2}, "% at least 1 match": 0.84, "avg #matches": 3.32, "max #matches of a user": 19, "min #matches of a user": 0, "avg #potential": 4.55, "max #potential of a user": 21, "min #potential of a user": 0, "avg matches score": 0.5303637329042243, "avg real score": 0.550661680667059, "avg similarity score": 0.7402847023666292, "avg quality score": 0.3610386589674889}}, "600": {"ss": 0.22037000954151154, "cluster_score": 0.7196460194648244, "#clusters": 117, "#instances": 414, "distribution": {"1": 39, "2": 25, "3": 15, "4": 11, "8": 8, "5": 5, "6": 4, "9": 2, "12": 2, "7": 2, "16": 2, "15": 1, "20": 1}, "avg/mean instances / cluster": 3.5384615384615383, "max instances of any cluster": 1, "min instances of any cluster": 20, "matches_results": {"distribution #matches": {"1": 26, "0": 19, "2": 15, "3": 8, "4": 7, "7": 6, "6": 4, "8": 3, "9": 2, "11": 2, "12": 2, "10": 2, "16": 2, "5": 1, "18": 1}, "distribution #potential": {"1": 27, "8": 16, "0": 11, "2": 10, "4": 7, "7": 7, "3": 6, "12": 6, "20": 3, "9": 2, "6": 2, "16": 2, "5": 1}, "distribution avg similarity range": {"80 - 85": 29, "75 - 80": 18, "85 - 90": 17, "0 - 5": 11, "70 - 75": 8, "65 - 70": 7, "90 - 95": 4, "95 - 100": 3, "60 - 65": 2, "55 - 60": 1}, "distribution avg quality range": {"25 - 30": 17, "30 - 35": 14, "0 - 5": 12, "20 - 25": 11, "40 - 45": 9, "45 - 50": 6, "35 - 40": 5, "10 - 15": 5, "70 - 75": 4, "80 - 85": 4, "15 - 20": 3, "85 - 90": 2, "55 - 60": 2, "90 - 95": 2, "75 - 80": 1, "100 - 105": 1, "50 - 55": 1, "65 - 70": 1}, "distribution avg real range": {"55 - 60": 21, "50 - 55": 17, "60 - 65": 11, "0 - 5": 11, "45 - 50": 10, "40 - 45": 7, "85 - 90": 5, "80 - 85": 5, "65 - 70": 5, "75 - 80": 3, "70 - 75": 2, "30 - 35": 1, "95 - 100": 1, "90 - 95": 1}, "distribution avg matches range": {"55 - 60": 32, "50 - 55": 14, "60 - 65": 12, "65 - 70": 6, "85 - 90": 5, "80 - 85": 5, "75 - 80": 3, "70 - 75": 2, "95 - 100": 1, "90 - 95": 1}, "distribution matches range": {"50 - 55": 104, "55 - 60": 101, "60 - 65": 57, "65 - 70": 20, "70 - 75": 15, "80 - 85": 13, "90 - 95": 11, "85 - 90": 8, "75 - 80": 6, "95 - 100": 2}, "% at least 1 match": 0.81, "avg #matches": 3.37, "max #matches of a user": 18, "min #matches of a user": 0, "avg #potential": 4.69, "max #potential of a user": 20, "min #potential of a user": 0, "avg matches score": 0.513019355149934, "avg real score": 0.5334976757121979, "avg similarity score": 0.7166932082873961, "avg quality score": 0.35030214313699953}}, "700": {"ss": 0.2295772284269333, "cluster_score": 0.7713584949502273, "#clusters": 126, "#instances": 459, "distribution": {"1": 44, "2": 26, "3": 18, "8": 9, "4": 9, "7": 5, "9": 3, "6": 3, "5": 2, "17": 1, "11": 1, "14": 1, "19": 1, "12": 1, "20": 1, "18": 1}, "avg/mean instances / cluster": 3.642857142857143, "max instances of any cluster": 1, "min instances of any cluster": 18, "matches_results": {"distribution #matches": {"0": 24, "1": 22, "2": 14, "3": 10, "8": 9, "4": 5, "7": 4, "6": 3, "11": 2, "10": 2, "14": 1, "5": 1, "18": 1, "12": 1, "17": 1}, "distribution #potential": {"8": 21, "1": 21, "0": 18, "2": 12, "3": 8, "12": 4, "9": 3, "6": 3, "19": 3, "7": 2, "14": 2, "4": 1, "5": 1, "18": 1}, "distribution avg similarity range": {"80 - 85": 26, "75 - 80": 18, "0 - 5": 18, "85 - 90": 16, "70 - 75": 8, "65 - 70": 5, "90 - 95": 4, "95 - 100": 3, "60 - 65": 2}, "distribution avg quality range": {"0 - 5": 19, "25 - 30": 13, "30 - 35": 11, "20 - 25": 11, "35 - 40": 8, "70 - 75": 6, "40 - 45": 6, "15 - 20": 4, "10 - 15": 4, "45 - 50": 4, "80 - 85": 3, "85 - 90": 2, "55 - 60": 2, "90 - 95": 2, "100 - 105": 1, "50 - 55": 1, "65 - 70": 1, "60 - 65": 1, "75 - 80": 1}, "distribution avg real range": {"0 - 5": 18, "50 - 55": 18, "55 - 60": 15, "45 - 50": 12, "60 - 65": 10, "80 - 85": 5, "75 - 80": 5, "65 - 70": 4, "85 - 90": 3, "40 - 45": 3, "70 - 75": 3, "90 - 95": 2, "30 - 35": 1, "95 - 100": 1}, "distribution avg matches range": {"55 - 60": 30, "50 - 55": 12, "60 - 65": 11, "80 - 85": 5, "75 - 80": 5, "65 - 70": 4, "85 - 90": 3, "70 - 75": 3, "90 - 95": 2, "95 - 100": 1}, "distribution matches range": {"55 - 60": 95, "50 - 55": 94, "60 - 65": 50, "65 - 70": 21, "80 - 85": 17, "70 - 75": 16, "90 - 95": 15, "85 - 90": 9, "75 - 80": 7, "95 - 100": 2}, "% at least 1 match": 0.76, "avg #matches": 3.26, "max #matches of a user": 18, "min #matches of a user": 0, "avg #potential": 4.56, "max #potential of a user": 19, "min #potential of a user": 0, "avg matches score": 0.4864727614118279, "avg real score": 0.49848986436573905, "avg similarity score": 0.6647000058973792, "avg quality score": 0.33227972283409896}}, "800": {"ss": 0.2103988230228424, "cluster_score": 0.8306290373329479, "#clusters": 135, "#instances": 502, "distribution": {"1": 49, "2": 26, "3": 14, "4": 11, "5": 9, "7": 6, "8": 4, "6": 4, "10": 3, "21": 2, "12": 2, "15": 1, "22": 1, "9": 1, "11": 1, "19": 1}, "avg/mean instances / cluster": 3.7185185185185183, "max instances of any cluster": 1, "min instances of any cluster": 19, "matches_results": {"distribution #matches": {"1": 27, "2": 21, "0": 15, "4": 5, "8": 4, "3": 4, "6": 4, "7": 4, "10": 3, "5": 3, "11": 2, "19": 2, "15": 1, "13": 1, "16": 1, "12": 1, "9": 1, "21": 1}, "distribution #potential": {"1": 24, "2": 22, "7": 12, "8": 9, "0": 6, "3": 4, "12": 4, "4": 4, "22": 4, "10": 3, "6": 3, "15": 2, "19": 2, "5": 1}, "distribution avg similarity range": {"80 - 85": 34, "75 - 80": 20, "85 - 90": 13, "70 - 75": 10, "65 - 70": 6, "0 - 5": 6, "90 - 95": 4, "95 - 100": 4, "60 - 65": 3}, "distribution avg quality range": {"25 - 30": 20, "20 - 25": 10, "30 - 35": 9, "35 - 40": 8, "40 - 45": 7, "0 - 5": 7, "45 - 50": 6, "70 - 75": 5, "10 - 15": 5, "80 - 85": 4, "15 - 20": 3, "5 - 10": 3, "75 - 80": 2, "100 - 105": 2, "50 - 55": 2, "90 - 95": 2, "55 - 60": 2, "60 - 65": 1, "85 - 90": 1, "65 - 70": 1}, "distribution avg real range": {"50 - 55": 22, "60 - 65": 15, "55 - 60": 14, "45 - 50": 8, "40 - 45": 8, "0 - 5": 6, "80 - 85": 5, "75 - 80": 5, "65 - 70": 4, "85 - 90": 3, "70 - 75": 3, "95 - 100": 2, "35 - 40": 2, "90 - 95": 2, "30 - 35": 1}, "distribution avg matches range": {"55 - 60": 25, "50 - 55": 20, "60 - 65": 16, "80 - 85": 5, "75 - 80": 5, "65 - 70": 4, "85 - 90": 3, "70 - 75": 3, "95 - 100": 2, "90 - 95": 2}, "distribution matches range": {"50 - 55": 114, "55 - 60": 98, "60 - 65": 54, "65 - 70": 25, "70 - 75": 21, "80 - 85": 20, "75 - 80": 17, "90 - 95": 15, "85 - 90": 8, "95 - 100": 4}, "% at least 1 match": 0.85, "avg #matches": 3.76, "max #matches of a user": 21, "min #matches of a user": 0, "avg #potential": 5.09, "max #potential of a user": 22, "min #potential of a user": 0, "avg matches score": 0.541435384796498, "avg real score": 0.5651567613899441, "avg similarity score": 0.7590912681036996, "avg quality score": 0.3712222546761885}}, "900": {"ss": 0.20011281967163086, "cluster_score": 0.8735967605957214, "#clusters": 140, "#instances": 536, "distribution": {"1": 51, "2": 28, "3": 15, "6": 8, "5": 8, "4": 6, "8": 6, "7": 4, "22": 3, "9": 3, "11": 2, "10": 2, "12": 1, "16": 1, "13": 1, "20": 1}, "avg/mean instances / cluster": 3.8285714285714287, "max instances of any cluster": 1, "min instances of any cluster": 20, "matches_results": {"distribution #matches": {"1": 24, "2": 15, "0": 13, "3": 9, "9": 8, "4": 6, "8": 5, "5": 5, "12": 4, "6": 2, "16": 2, "20": 2, "7": 2, "11": 1, "14": 1, "21": 1}, "distribution #potential": {"1": 20, "2": 15, "5": 10, "8": 9, "3": 8, "9": 7, "0": 7, "10": 6, "22": 5, "13": 4, "7": 3, "16": 2, "20": 2, "6": 1, "4": 1}, "distribution avg similarity range": {"80 - 85": 36, "75 - 80": 21, "85 - 90": 12, "70 - 75": 8, "0 - 5": 7, "65 - 70": 6, "90 - 95": 4, "95 - 100": 4, "60 - 65": 2}, "distribution avg quality range": {"25 - 30": 25, "20 - 25": 10, "35 - 40": 9, "40 - 45": 8, "0 - 5": 8, "30 - 35": 6, "80 - 85": 4, "45 - 50": 4, "15 - 20": 4, "70 - 75": 4, "10 - 15": 3, "100 - 105": 2, "85 - 90": 2, "50 - 55": 2, "65 - 70": 2, "90 - 95": 2, "55 - 60": 2, "5 - 10": 1, "60 - 65": 1, "75 - 80": 1}, "distribution avg real range": {"50 - 55": 26, "60 - 65": 17, "55 - 60": 12, "45 - 50": 10, "0 - 5": 7, "80 - 85": 5, "85 - 90": 4, "40 - 45": 4, "75 - 80": 4, "70 - 75": 3, "95 - 100": 2, "65 - 70": 2, "90 - 95": 2, "30 - 35": 1, "35 - 40": 1}, "distribution avg matches range": {"55 - 60": 24, "60 - 65": 21, "50 - 55": 20, "80 - 85": 5, "85 - 90": 4, "75 - 80": 4, "70 - 75": 3, "95 - 100": 2, "65 - 70": 2, "90 - 95": 2}, "distribution matches range": {"50 - 55": 143, "55 - 60": 108, "60 - 65": 68, "65 - 70": 28, "80 - 85": 22, "70 - 75": 21, "75 - 80": 17, "90 - 95": 15, "85 - 90": 8, "95 - 100": 4}, "% at least 1 match": 0.87, "avg #matches": 4.34, "max #matches of a user": 21, "min #matches of a user": 0, "avg #potential": 5.84, "max #potential of a user": 22, "min #potential of a user": 0, "avg matches score": 0.5537282949998915, "avg real score": 0.5635785936937546, "avg similarity score": 0.7529804222804816, "avg quality score": 0.37417676510702774}}, "1000": {"ss": 0.19539541006088257, "cluster_score": 0.906529071563016, "#clusters": 144, "#instances": 567, "distribution": {"1": 56, "2": 22, "3": 15, "4": 11, "7": 8, "10": 8, "6": 6, "5": 6, "23": 3, "8": 2, "11": 2, "9": 2, "17": 1, "16": 1, "18": 1}, "avg/mean instances / cluster": 3.9375, "max instances of any cluster": 1, "min instances of any cluster": 18, "matches_results": {"distribution #matches": {"1": 31, "2": 15, "0": 14, "3": 8, "4": 6, "10": 4, "9": 4, "5": 4, "8": 3, "14": 2, "16": 2, "23": 2, "13": 1, "12": 1, "7": 1, "11": 1, "22": 1}, "distribution #potential": {"1": 28, "2": 13, "10": 12, "4": 10, "0": 8, "8": 6, "3": 6, "23": 5, "16": 4, "17": 2, "6": 2, "5": 2, "7": 1, "9": 1}, "distribution avg similarity range": {"80 - 85": 36, "85 - 90": 15, "75 - 80": 14, "70 - 75": 9, "0 - 5": 8, "95 - 100": 6, "65 - 70": 5, "90 - 95": 4, "60 - 65": 3}, "distribution avg quality range": {"25 - 30": 19, "40 - 45": 9, "35 - 40": 9, "0 - 5": 9, "20 - 25": 9, "30 - 35": 7, "70 - 75": 5, "85 - 90": 5, "45 - 50": 4, "15 - 20": 4, "80 - 85": 3, "100 - 105": 3, "10 - 15": 3, "75 - 80": 2, "65 - 70": 2, "55 - 60": 2, "5 - 10": 1, "50 - 55": 1, "95 - 100": 1, "60 - 65": 1, "90 - 95": 1}, "distribution avg real range": {"50 - 55": 21, "60 - 65": 16, "55 - 60": 13, "45 - 50": 8, "0 - 5": 8, "85 - 90": 5, "40 - 45": 5, "80 - 85": 5, "75 - 80": 5, "90 - 95": 5, "70 - 75": 3, "95 - 100": 2, "65 - 70": 2, "30 - 35": 1, "35 - 40": 1}, "distribution avg matches range": {"55 - 60": 24, "60 - 65": 18, "50 - 55": 17, "85 - 90": 5, "80 - 85": 5, "75 - 80": 5, "90 - 95": 5, "70 - 75": 3, "95 - 100": 2, "65 - 70": 2}, "distribution matches range": {"50 - 55": 104, "55 - 60": 103, "60 - 65": 65, "65 - 70": 29, "80 - 85": 25, "70 - 75": 23, "90 - 95": 18, "75 - 80": 18, "85 - 90": 11, "95 - 100": 4}, "% at least 1 match": 0.86, "avg #matches": 4.0, "max #matches of a user": 23, "min #matches of a user": 0, "avg #potential": 5.31, "max #potential of a user": 23, "min #potential of a user": 0, "avg matches score": 0.5638101465923537, "avg real score": 0.5758591932633534, "avg similarity score": 0.7517473262807292, "avg quality score": 0.3999710602459776}}, "1100": {"ss": 0.19284185767173767, "cluster_score": 0.9497636403430136, "#clusters": 150, "#instances": 604, "distribution": {"1": 60, "2": 22, "4": 14, "3": 13, "7": 7, "10": 6, "8": 5, "5": 5, "6": 4, "9": 4, "23": 3, "11": 2, "16": 2, "14": 1, "19": 1, "15": 1}, "avg/mean instances / cluster": 4.026666666666666, "max instances of any cluster": 1, "min instances of any cluster": 15, "matches_results": {"distribution #matches": {"1": 34, "2": 19, "0": 12, "10": 5, "7": 5, "8": 3, "4": 3, "5": 3, "6": 2, "14": 2, "3": 2, "23": 2, "9": 1, "11": 1, "18": 1, "12": 1, "13": 1, "17": 1, "15": 1, "22": 1}, "distribution #potential": {"1": 31, "2": 18, "8": 14, "10": 6, "0": 6, "23": 5, "4": 4, "16": 3, "15": 3, "19": 2, "7": 2, "9": 2, "3": 2, "11": 1, "6": 1}, "distribution avg similarity range": {"80 - 85": 34, "85 - 90": 20, "75 - 80": 16, "70 - 75": 7, "95 - 100": 6, "0 - 5": 6, "90 - 95": 5, "60 - 65": 3, "65 - 70": 3}, "distribution avg quality range": {"25 - 30": 16, "20 - 25": 11, "40 - 45": 8, "35 - 40": 8, "30 - 35": 7, "70 - 75": 7, "0 - 5": 7, "45 - 50": 5, "10 - 15": 5, "85 - 90": 5, "80 - 85": 4, "60 - 65": 3, "100 - 105": 3, "15 - 20": 2, "50 - 55": 2, "55 - 60": 2, "5 - 10": 1, "65 - 70": 1, "95 - 100": 1, "75 - 80": 1, "90 - 95": 1}, "distribution avg real range": {"50 - 55": 17, "60 - 65": 16, "55 - 60": 13, "45 - 50": 8, "80 - 85": 6, "40 - 45": 6, "0 - 5": 6, "85 - 90": 5, "70 - 75": 5, "75 - 80": 5, "90 - 95": 5, "65 - 70": 4, "95 - 100": 2, "30 - 35": 1, "35 - 40": 1}, "distribution avg matches range": {"60 - 65": 20, "55 - 60": 19, "50 - 55": 17, "80 - 85": 6, "85 - 90": 5, "70 - 75": 5, "75 - 80": 5, "90 - 95": 5, "65 - 70": 4, "95 - 100": 2}, "distribution matches range": {"50 - 55": 120, "55 - 60": 96, "60 - 65": 63, "65 - 70": 34, "80 - 85": 27, "70 - 75": 23, "90 - 95": 19, "75 - 80": 18, "85 - 90": 12, "95 - 100": 5}, "% at least 1 match": 0.88, "avg #matches": 4.17, "max #matches of a user": 23, "min #matches of a user": 0, "avg #potential": 5.56, "max #potential of a user": 23, "min #potential of a user": 0, "avg matches score": 0.5832361474696789, "avg real score": 0.5954810796967321, "avg similarity score": 0.7745765311499284, "avg quality score": 0.41638562824353587}}, "1200": {"ss": 0.2025424838066101, "cluster_score": 0.9917946593482281, "#clusters": 155, "#instances": 626, "distribution": {"1": 58, "2": 27, "3": 15, "4": 14, "7": 7, "6": 6, "8": 5, "11": 4, "9": 4, "5": 4, "24": 2, "16": 2, "20": 1, "12": 1, "13": 1, "15": 1, "21": 1, "10": 1, "17": 1}, "avg/mean instances / cluster": 4.038709677419355, "max instances of any cluster": 1, "min instances of any cluster": 17, "matches_results": {"distribution #matches": {"1": 32, "0": 19, "2": 16, "9": 4, "7": 4, "6": 4, "3": 4, "8": 2, "14": 2, "4": 2, "21": 2, "5": 2, "11": 1, "10": 1, "19": 1, "12": 1, "18": 1, "17": 1, "23": 1}, "distribution #potential": {"1": 31, "2": 15, "0": 12, "7": 8, "8": 5, "3": 5, "9": 4, "4": 4, "16": 3, "24": 3, "11": 2, "20": 2, "21": 2, "6": 2, "10": 1, "17": 1}, "distribution avg similarity range": {"80 - 85": 31, "85 - 90": 20, "75 - 80": 14, "0 - 5": 12, "70 - 75": 7, "90 - 95": 6, "95 - 100": 6, "65 - 70": 3, "60 - 65": 1}, "distribution avg quality range": {"25 - 30": 15, "0 - 5": 13, "40 - 45": 9, "20 - 25": 8, "70 - 75": 7, "30 - 35": 6, "35 - 40": 6, "80 - 85": 5, "45 - 50": 5, "10 - 15": 5, "85 - 90": 5, "15 - 20": 3, "60 - 65": 3, "100 - 105": 3, "50 - 55": 2, "55 - 60": 2, "65 - 70": 1, "95 - 100": 1, "90 - 95": 1}, "distribution avg real range": {"55 - 60": 14, "60 - 65": 14, "0 - 5": 12, "50 - 55": 12, "45 - 50": 8, "80 - 85": 7, "40 - 45": 6, "85 - 90": 5, "70 - 75": 5, "65 - 70": 5, "90 - 95": 5, "75 - 80": 4, "95 - 100": 2, "30 - 35": 1}, "distribution avg matches range": {"55 - 60": 18, "60 - 65": 18, "50 - 55": 12, "80 - 85": 7, "85 - 90": 5, "70 - 75": 5, "65 - 70": 5, "90 - 95": 5, "75 - 80": 4, "95 - 100": 2}, "distribution matches range": {"50 - 55": 103, "55 - 60": 82, "60 - 65": 58, "65 - 70": 32, "80 - 85": 26, "70 - 75": 22, "90 - 95": 18, "75 - 80": 18, "85 - 90": 13, "95 - 100": 6}, "% at least 1 match": 0.81, "avg #matches": 3.78, "max #matches of a user": 23, "min #matches of a user": 0, "avg #potential": 4.87, "max #potential of a user": 24, "min #potential of a user": 0, "avg matches score": 0.5454785284098391, "avg real score": 0.5664133190515321, "avg similarity score": 0.7298816046854599, "avg quality score": 0.40294503341760435}}, "1300": {"ss": 0.20646671950817108, "cluster_score": 1.0397531101964617, "#clusters": 162, "#instances": 668, "distribution": {"1": 63, "2": 24, "3": 18, "4": 12, "6": 9, "8": 5, "5": 5, "9": 5, "7": 4, "10": 4, "14": 4, "11": 2, "16": 2, "27": 1, "22": 1, "25": 1, "15": 1, "24": 1}, "avg/mean instances / cluster": 4.1234567901234565, "max instances of any cluster": 1, "min instances of any cluster": 24, "matches_results": {"distribution #matches": {"1": 32, "0": 18, "2": 18, "8": 4, "9": 4, "3": 4, "4": 4, "14": 3, "24": 3, "7": 2, "6": 2, "10": 1, "21": 1, "13": 1, "11": 1, "5": 1, "19": 1}, "distribution #potential": {"1": 28, "2": 22, "9": 10, "0": 10, "6": 6, "4": 4, "16": 3, "3": 3, "25": 3, "14": 2, "10": 2, "22": 2, "5": 2, "24": 2, "8": 1}, "distribution avg similarity range": {"80 - 85": 34, "85 - 90": 17, "75 - 80": 14, "0 - 5": 10, "70 - 75": 8, "90 - 95": 6, "95 - 100": 5, "65 - 70": 4, "55 - 60": 1, "60 - 65": 1}, "distribution avg quality range": {"25 - 30": 13, "0 - 5": 11, "40 - 45": 9, "20 - 25": 9, "30 - 35": 8, "70 - 75": 6, "80 - 85": 5, "15 - 20": 5, "35 - 40": 5, "10 - 15": 5, "85 - 90": 5, "45 - 50": 4, "60 - 65": 3, "50 - 55": 3, "100 - 105": 3, "55 - 60": 2, "5 - 10": 1, "65 - 70": 1, "95 - 100": 1, "90 - 95": 1}, "distribution avg real range": {"55 - 60": 15, "60 - 65": 15, "50 - 55": 11, "45 - 50": 10, "0 - 5": 10, "80 - 85": 6, "70 - 75": 6, "40 - 45": 6, "90 - 95": 6, "85 - 90": 5, "75 - 80": 4, "65 - 70": 3, "35 - 40": 1, "30 - 35": 1, "95 - 100": 1}, "distribution avg matches range": {"55 - 60": 21, "60 - 65": 17, "50 - 55": 13, "80 - 85": 6, "70 - 75": 6, "90 - 95": 6, "85 - 90": 5, "75 - 80": 4, "65 - 70": 3, "95 - 100": 1}, "distribution matches range": {"50 - 55": 100, "55 - 60": 84, "60 - 65": 56, "65 - 70": 30, "80 - 85": 29, "70 - 75": 25, "90 - 95": 21, "75 - 80": 20, "85 - 90": 14, "95 - 100": 4}, "% at least 1 match": 0.8200000000000001, "avg #matches": 3.83, "max #matches of a user": 24, "min #matches of a user": 0, "avg #potential": 5.04, "max #potential of a user": 25, "min #potential of a user": 0, "avg matches score": 0.5473891170777055, "avg real score": 0.5706594003052348, "avg similarity score": 0.7407998100841652, "avg quality score": 0.40051899052630424}}, "1400": {"ss": 0.20309682190418243, "cluster_score": 1.0773153440198489, "#clusters": 164, "#instances": 690, "distribution": {"1": 62, "2": 26, "3": 15, "6": 12, "4": 11, "5": 7, "9": 5, "8": 5, "7": 4, "10": 3, "25": 2, "13": 2, "16": 2, "12": 2, "17": 1, "22": 1, "26": 1, "14": 1, "15": 1, "11": 1}, "avg/mean instances / cluster": 4.2073170731707314, "max instances of any cluster": 1, "min instances of any cluster": 11, "matches_results": {"distribution #matches": {"1": 34, "2": 17, "0": 16, "8": 4, "7": 4, "3": 4, "4": 4, "25": 3, "13": 2, "6": 2, "9": 2, "5": 2, "16": 1, "11": 1, "21": 1, "15": 1, "12": 1, "20": 1}, "distribution #potential": {"1": 28, "2": 22, "0": 9, "8": 8, "7": 6, "16": 4, "4": 4, "6": 4, "26": 3, "22": 2, "5": 2, "3": 2, "25": 2, "12": 1, "11": 1, "9": 1, "13": 1}, "distribution avg similarity range": {"80 - 85": 33, "85 - 90": 19, "75 - 80": 14, "0 - 5": 9, "70 - 75": 8, "90 - 95": 7, "95 - 100": 5, "65 - 70": 4, "55 - 60": 1}, "distribution avg quality range": {"25 - 30": 15, "20 - 25": 10, "40 - 45": 9, "0 - 5": 9, "30 - 35": 7, "10 - 15": 7, "70 - 75": 6, "80 - 85": 5, "35 - 40": 5, "85 - 90": 5, "45 - 50": 4, "15 - 20": 4, "60 - 65": 3, "50 - 55": 3, "100 - 105": 3, "55 - 60": 2, "90 - 95": 2, "65 - 70": 1}, "distribution avg real range": {"55 - 60": 14, "60 - 65": 14, "50 - 55": 14, "45 - 50": 10, "0 - 5": 9, "80 - 85": 6, "70 - 75": 6, "90 - 95": 6, "85 - 90": 5, "40 - 45": 5, "65 - 70": 4, "75 - 80": 4, "35 - 40": 2, "95 - 100": 1}, "distribution avg matches range": {"55 - 60": 22, "60 - 65": 16, "50 - 55": 14, "80 - 85": 6, "70 - 75": 6, "90 - 95": 6, "85 - 90": 5, "65 - 70": 4, "75 - 80": 4, "95 - 100": 1}, "distribution matches range": {"50 - 55": 103, "55 - 60": 86, "60 - 65": 53, "65 - 70": 32, "80 - 85": 30, "70 - 75": 24, "90 - 95": 23, "75 - 80": 21, "85 - 90": 15, "95 - 100": 5}, "% at least 1 match": 0.84, "avg #matches": 3.92, "max #matches of a user": 25, "min #matches of a user": 0, "avg #potential": 5.15, "max #potential of a user": 26, "min #potential of a user": 0, "avg matches score": 0.5589918672595958, "avg real score": 0.5784129014389686, "avg similarity score": 0.7523229609039186, "avg quality score": 0.4045028419740186}}, "1500": {"ss": 0.20547395944595337, "cluster_score": 1.0878530604486136, "#clusters": 168, "#instances": 715, "distribution": {"1": 67, "2": 24, "4": 17, "3": 14, "6": 8, "9": 6, "10": 4, "8": 4, "7": 4, "5": 4, "16": 3, "11": 3, "28": 2, "12": 2, "14": 2, "19": 1, "13": 1, "18": 1, "29": 1}, "avg/mean instances / cluster": 4.255952380952381, "max instances of any cluster": 1, "min instances of any cluster": 29, "matches_results": {"distribution #matches": {"1": 37, "2": 17, "0": 15, "4": 6, "9": 4, "7": 4, "10": 2, "3": 2, "29": 2, "8": 2, "16": 1, "18": 1, "17": 1, "5": 1, "15": 1, "14": 1, "6": 1, "12": 1, "21": 1}, "distribution #potential": {"1": 31, "2": 15, "0": 9, "3": 7, "8": 7, "10": 6, "4": 5, "7": 3, "18": 3, "9": 2, "19": 2, "6": 2, "5": 2, "29": 2, "28": 2, "16": 1, "12": 1}, "distribution avg similarity range": {"80 - 85": 33, "85 - 90": 17, "75 - 80": 15, "0 - 5": 9, "70 - 75": 8, "90 - 95": 7, "95 - 100": 6, "65 - 70": 4, "60 - 65": 1}, "distribution avg quality range": {"25 - 30": 16, "40 - 45": 11, "0 - 5": 9, "20 - 25": 9, "35 - 40": 7, "85 - 90": 7, "15 - 20": 6, "80 - 85": 5, "10 - 15": 5, "70 - 75": 5, "45 - 50": 4, "30 - 35": 4, "50 - 55": 3, "100 - 105": 3, "60 - 65": 2, "90 - 95": 2, "65 - 70": 1, "55 - 60": 1}, "distribution avg real range": {"50 - 55": 18, "60 - 65": 16, "55 - 60": 10, "0 - 5": 9, "40 - 45": 8, "45 - 50": 8, "90 - 95": 7, "85 - 90": 5, "80 - 85": 5, "70 - 75": 4, "65 - 70": 4, "75 - 80": 4, "95 - 100": 2}, "distribution avg matches range": {"60 - 65": 19, "50 - 55": 18, "55 - 60": 17, "90 - 95": 7, "85 - 90": 5, "80 - 85": 5, "70 - 75": 4, "65 - 70": 4, "75 - 80": 4, "95 - 100": 2}, "distribution matches range": {"50 - 55": 101, "55 - 60": 75, "60 - 65": 47, "65 - 70": 33, "80 - 85": 32, "90 - 95": 27, "75 - 80": 24, "70 - 75": 22, "85 - 90": 17, "95 - 100": 5}, "% at least 1 match": 0.85, "avg #matches": 3.83, "max #matches of a user": 29, "min #matches of a user": 0, "avg #potential": 5.13, "max #potential of a user": 29, "min #potential of a user": 0, "avg matches score": 0.5659847559877683, "avg real score": 0.5805117636014163, "avg similarity score": 0.7520611131867867, "avg quality score": 0.4089624140160458}}, "1600": {"ss": 0.20964571833610535, "cluster_score": 1.1015158525948954, "#clusters": 170, "#instances": 726, "distribution": {"1": 67, "2": 25, "3": 20, "6": 9, "4": 8, "10": 8, "5": 7, "9": 5, "8": 5, "12": 3, "29": 2, "16": 2, "14": 2, "7": 2, "15": 1, "20": 1, "27": 1, "22": 1, "11": 1}, "avg/mean instances / cluster": 4.270588235294118, "max instances of any cluster": 1, "min instances of any cluster": 11, "matches_results": {"distribution #matches": {"1": 36, "2": 16, "0": 15, "3": 6, "9": 4, "8": 3, "7": 3, "4": 3, "10": 2, "19": 2, "6": 2, "29": 2, "14": 1, "21": 1, "17": 1, "12": 1, "20": 1, "5": 1}, "distribution #potential": {"1": 30, "2": 15, "3": 13, "9": 10, "0": 8, "6": 4, "22": 3, "8": 3, "10": 2, "20": 2, "7": 2, "4": 2, "29": 2, "27": 2, "14": 1, "12": 1}, "distribution avg similarity range": {"80 - 85": 33, "85 - 90": 17, "75 - 80": 16, "0 - 5": 8, "70 - 75": 8, "90 - 95": 7, "95 - 100": 6, "65 - 70": 4, "60 - 65": 1}, "distribution avg quality range": {"25 - 30": 17, "40 - 45": 10, "15 - 20": 9, "0 - 5": 8, "20 - 25": 8, "35 - 40": 7, "85 - 90": 7, "45 - 50": 4, "10 - 15": 4, "80 - 85": 4, "30 - 35": 4, "70 - 75": 3, "65 - 70": 3, "100 - 105": 3, "60 - 65": 2, "55 - 60": 2, "50 - 55": 2, "75 - 80": 1, "90 - 95": 1, "95 - 100": 1}, "distribution avg real range": {"50 - 55": 18, "60 - 65": 15, "55 - 60": 10, "45 - 50": 10, "0 - 5": 8, "40 - 45": 7, "90 - 95": 7, "70 - 75": 6, "85 - 90": 5, "80 - 85": 5, "65 - 70": 4, "75 - 80": 3, "95 - 100": 2}, "distribution avg matches range": {"60 - 65": 19, "55 - 60": 17, "50 - 55": 17, "90 - 95": 7, "70 - 75": 6, "85 - 90": 5, "80 - 85": 5, "65 - 70": 4, "75 - 80": 3, "95 - 100": 2}, "distribution matches range": {"50 - 55": 107, "55 - 60": 80, "60 - 65": 47, "80 - 85": 35, "65 - 70": 35, "75 - 80": 25, "90 - 95": 24, "70 - 75": 22, "85 - 90": 16, "95 - 100": 5}, "% at least 1 match": 0.85, "avg #matches": 3.96, "max #matches of a user": 29, "min #matches of a user": 0, "avg #potential": 5.23, "max #potential of a user": 29, "min #potential of a user": 0, "avg matches score": 0.5659364041091051, "avg real score": 0.5850178581346727, "avg similarity score": 0.7596065566227258, "avg quality score": 0.4104291596466195}}, "1700": {"ss": 0.21220646798610687, "cluster_score": 1.1287533431111743, "#clusters": 168, "#instances": 744, "distribution": {"1": 63, "2": 26, "3": 16, "4": 12, "5": 9, "6": 8, "8": 5, "7": 4, "10": 4, "9": 4, "18": 2, "12": 2, "13": 2, "16": 2, "11": 2, "30": 1, "25": 1, "24": 1, "17": 1, "15": 1, "14": 1, "31": 1}, "avg/mean instances / cluster": 4.428571428571429, "max instances of any cluster": 1, "min instances of any cluster": 31, "matches_results": {"distribution #matches": {"1": 34, "0": 15, "2": 15, "3": 7, "8": 4, "10": 3, "5": 3, "7": 3, "6": 2, "4": 2, "31": 2, "15": 1, "9": 1, "17": 1, "23": 1, "21": 1, "19": 1, "11": 1, "12": 1, "18": 1, "16": 1}, "distribution #potential": {"1": 28, "2": 15, "0": 9, "4": 7, "11": 7, "8": 7, "3": 6, "24": 3, "5": 3, "18": 2, "6": 2, "7": 2, "31": 2, "25": 2, "15": 1, "10": 1, "9": 1, "12": 1, "16": 1}, "distribution avg similarity range": {"80 - 85": 34, "85 - 90": 17, "75 - 80": 15, "0 - 5": 9, "70 - 75": 8, "90 - 95": 7, "95 - 100": 5, "65 - 70": 4, "60 - 65": 1}, "distribution avg quality range": {"25 - 30": 16, "40 - 45": 12, "0 - 5": 9, "15 - 20": 8, "35 - 40": 7, "85 - 90": 7, "10 - 15": 6, "20 - 25": 6, "80 - 85": 5, "45 - 50": 4, "30 - 35": 4, "70 - 75": 3, "65 - 70": 3, "60 - 65": 2, "55 - 60": 2, "50 - 55": 2, "100 - 105": 2, "90 - 95": 2}, "distribution avg real range": {"60 - 65": 17, "50 - 55": 16, "55 - 60": 10, "0 - 5": 9, "45 - 50": 9, "40 - 45": 8, "90 - 95": 7, "70 - 75": 6, "85 - 90": 5, "80 - 85": 5, "65 - 70": 4, "75 - 80": 3, "95 - 100": 1}, "distribution avg matches range": {"60 - 65": 21, "55 - 60": 17, "50 - 55": 16, "90 - 95": 7, "70 - 75": 6, "85 - 90": 5, "80 - 85": 5, "65 - 70": 4, "75 - 80": 3, "95 - 100": 1}, "distribution matches range": {"50 - 55": 112, "55 - 60": 84, "60 - 65": 63, "65 - 70": 35, "80 - 85": 33, "70 - 75": 26, "90 - 95": 26, "75 - 80": 26, "85 - 90": 18, "95 - 100": 3}, "% at least 1 match": 0.85, "avg #matches": 4.26, "max #matches of a user": 31, "min #matches of a user": 0, "avg #potential": 5.6, "max #potential of a user": 31, "min #potential of a user": 0, "avg matches score": 0.5625369598147427, "avg real score": 0.5764854418303104, "avg similarity score": 0.7508114661967297, "avg quality score": 0.40215941746389094}}, "1800": {"ss": 0.2236100435256958, "cluster_score": 1.1396632312633324, "#clusters": 170, "#instances": 750, "distribution": {"1": 61, "2": 30, "3": 21, "5": 11, "10": 7, "4": 6, "6": 6, "7": 5, "9": 4, "8": 3, "13": 3, "21": 2, "11": 2, "35": 1, "12": 1, "18": 1, "24": 1, "17": 1, "15": 1, "14": 1, "32": 1, "16": 1}, "avg/mean instances / cluster": 4.411764705882353, "max instances of any cluster": 1, "min instances of any cluster": 16, "matches_results": {"distribution #matches": {"1": 31, "2": 21, "0": 15, "3": 7, "5": 5, "10": 2, "4": 2, "6": 2, "17": 2, "32": 2, "9": 2, "7": 2, "8": 2, "15": 1, "20": 1, "21": 1, "18": 1, "16": 1}, "distribution #potential": {"1": 26, "2": 16, "3": 15, "0": 10, "5": 8, "21": 5, "11": 4, "9": 3, "10": 2, "6": 2, "7": 2, "32": 2, "24": 2, "15": 1, "16": 1, "8": 1}, "distribution avg similarity range": {"80 - 85": 29, "75 - 80": 20, "85 - 90": 19, "0 - 5": 10, "70 - 75": 7, "90 - 95": 6, "95 - 100": 6, "65 - 70": 2, "60 - 65": 1}, "distribution avg quality range": {"25 - 30": 16, "40 - 45": 11, "0 - 5": 10, "20 - 25": 9, "85 - 90": 8, "15 - 20": 7, "35 - 40": 7, "80 - 85": 5, "10 - 15": 5, "45 - 50": 4, "30 - 35": 3, "70 - 75": 3, "60 - 65": 2, "55 - 60": 2, "50 - 55": 2, "65 - 70": 2, "100 - 105": 2, "95 - 100": 1, "90 - 95": 1}, "distribution avg real range": {"60 - 65": 18, "50 - 55": 16, "45 - 50": 14, "0 - 5": 10, "55 - 60": 9, "90 - 95": 8, "85 - 90": 5, "70 - 75": 5, "40 - 45": 4, "80 - 85": 4, "75 - 80": 4, "65 - 70": 2, "95 - 100": 1}, "distribution avg matches range": {"60 - 65": 21, "50 - 55": 18, "55 - 60": 17, "90 - 95": 8, "85 - 90": 5, "70 - 75": 5, "80 - 85": 4, "75 - 80": 4, "65 - 70": 2, "95 - 100": 1}, "distribution matches range": {"50 - 55": 99, "55 - 60": 75, "60 - 65": 60, "80 - 85": 33, "65 - 70": 32, "90 - 95": 27, "70 - 75": 25, "75 - 80": 24, "85 - 90": 17, "95 - 100": 3}, "% at least 1 match": 0.85, "avg #matches": 3.95, "max #matches of a user": 32, "min #matches of a user": 0, "avg #potential": 5.16, "max #potential of a user": 32, "min #potential of a user": 0, "avg matches score": 0.5622328694137417, "avg real score": 0.5720148295991146, "avg similarity score": 0.7443272321390426, "avg quality score": 0.3997024270591866}}, "1900": {"ss": 0.23453857004642487, "cluster_score": 1.1677468130429878, "#clusters": 173, "#instances": 761, "distribution": {"1": 60, "2": 32, "3": 21, "6": 9, "5": 9, "4": 8, "11": 6, "7": 5, "12": 4, "8": 4, "9": 2, "15": 2, "10": 2, "36": 1, "19": 1, "21": 1, "25": 1, "20": 1, "16": 1, "14": 1, "13": 1, "30": 1}, "avg/mean instances / cluster": 4.398843930635838, "max instances of any cluster": 1, "min instances of any cluster": 30, "matches_results": {"distribution #matches": {"1": 30, "2": 20, "0": 15, "3": 9, "6": 5, "5": 4, "11": 3, "15": 2, "20": 2, "30": 2, "7": 2, "4": 1, "17": 1, "16": 1, "9": 1, "19": 1, "8": 1}, "distribution #potential": {"1": 24, "2": 21, "3": 11, "0": 10, "6": 9, "11": 3, "20": 3, "10": 3, "8": 3, "15": 2, "21": 2, "5": 2, "30": 2, "25": 2, "4": 1, "7": 1, "12": 1}, "distribution avg similarity range": {"80 - 85": 29, "75 - 80": 18, "85 - 90": 17, "0 - 5": 10, "70 - 75": 9, "90 - 95": 7, "95 - 100": 7, "65 - 70": 2, "60 - 65": 1}, "distribution avg quality range": {"25 - 30": 20, "40 - 45": 10, "0 - 5": 10, "35 - 40": 8, "85 - 90": 8, "20 - 25": 8, "15 - 20": 6, "10 - 15": 6, "80 - 85": 5, "70 - 75": 5, "45 - 50": 3, "60 - 65": 3, "100 - 105": 3, "30 - 35": 1, "55 - 60": 1, "65 - 70": 1, "95 - 100": 1, "90 - 95": 1}, "distribution avg real range": {"50 - 55": 19, "60 - 65": 18, "0 - 5": 10, "45 - 50": 10, "90 - 95": 9, "55 - 60": 8, "40 - 45": 6, "85 - 90": 5, "80 - 85": 5, "75 - 80": 5, "70 - 75": 3, "95 - 100": 1, "65 - 70": 1}, "distribution avg matches range": {"50 - 55": 21, "60 - 65": 20, "55 - 60": 15, "90 - 95": 9, "85 - 90": 5, "80 - 85": 5, "75 - 80": 5, "70 - 75": 3, "95 - 100": 1, "65 - 70": 1}, "distribution matches range": {"50 - 55": 102, "55 - 60": 75, "60 - 65": 60, "80 - 85": 34, "90 - 95": 30, "65 - 70": 30, "75 - 80": 24, "70 - 75": 21, "85 - 90": 17, "95 - 100": 4}, "% at least 1 match": 0.85, "avg #matches": 3.97, "max #matches of a user": 30, "min #matches of a user": 0, "avg #potential": 5.15, "max #potential of a user": 30, "min #potential of a user": 0, "avg matches score": 0.5642389977767635, "avg real score": 0.5752961169781573, "avg similarity score": 0.745277692324723, "avg quality score": 0.40531454163159164}}, "1999": {"ss": 0.2361508160829544, "cluster_score": 1.1865205428716796, "#clusters": 174, "#instances": 777, "distribution": {"1": 58, "2": 37, "3": 17, "4": 11, "5": 10, "6": 7, "7": 5, "11": 4, "12": 3, "10": 3, "9": 2, "14": 2, "13": 2, "16": 2, "8": 2, "15": 2, "34": 1, "18": 1, "22": 1, "24": 1, "21": 1, "27": 1, "17": 1}, "avg/mean instances / cluster": 4.4655172413793105, "max instances of any cluster": 1, "min instances of any cluster": 17, "matches_results": {"distribution #matches": {"1": 29, "2": 20, "0": 13, "3": 8, "6": 6, "11": 3, "4": 3, "5": 3, "21": 2, "18": 2, "17": 2, "27": 2, "9": 2, "16": 1, "12": 1, "10": 1, "8": 1, "7": 1}, "distribution #potential": {"1": 25, "2": 21, "11": 7, "0": 7, "6": 7, "3": 7, "4": 6, "21": 3, "5": 3, "22": 2, "7": 2, "27": 2, "24": 2, "10": 2, "16": 1, "12": 1, "13": 1, "17": 1}, "distribution avg similarity range": {"80 - 85": 31, "85 - 90": 18, "75 - 80": 17, "70 - 75": 9, "90 - 95": 7, "0 - 5": 7, "95 - 100": 7, "65 - 70": 3, "60 - 65": 1}, "distribution avg quality range": {"25 - 30": 20, "20 - 25": 11, "40 - 45": 10, "35 - 40": 9, "85 - 90": 8, "0 - 5": 7, "80 - 85": 5, "10 - 15": 5, "70 - 75": 5, "15 - 20": 4, "60 - 65": 4, "45 - 50": 3, "100 - 105": 3, "30 - 35": 1, "55 - 60": 1, "5 - 10": 1, "65 - 70": 1, "95 - 100": 1, "90 - 95": 1}, "distribution avg real range": {"50 - 55": 21, "60 - 65": 18, "90 - 95": 9, "45 - 50": 9, "55 - 60": 8, "0 - 5": 7, "40 - 45": 6, "85 - 90": 5, "80 - 85": 5, "75 - 80": 5, "70 - 75": 4, "95 - 100": 1, "35 - 40": 1, "65 - 70": 1}, "distribution avg matches range": {"50 - 55": 23, "60 - 65": 20, "55 - 60": 14, "90 - 95": 9, "85 - 90": 5, "80 - 85": 5, "75 - 80": 5, "70 - 75": 4, "95 - 100": 1, "65 - 70": 1}, "distribution matches range": {"50 - 55": 118, "55 - 60": 85, "60 - 65": 67, "80 - 85": 31, "90 - 95": 30, "65 - 70": 30, "70 - 75": 24, "75 - 80": 23, "85 - 90": 14, "95 - 100": 4}, "% at least 1 match": 0.87, "avg #matches": 4.26, "max #matches of a user": 27, "min #matches of a user": 0, "avg #potential": 5.47, "max #potential of a user": 27, "min #potential of a user": 0, "avg matches score": 0.5772664080478667, "avg real score": 0.5931306701309926, "avg similarity score": 0.7692300395143431, "avg quality score": 0.417031300747642}}}}